<HelpBalloon>
	<title>Archiv</title>
	<content><![CDATA[<P STYLE="margin-bottom: 0in">Die Auswahlliste <FONT FACE="Tahoma, sans-serif">Archiv</FONT>
dient dazu, das Mailing einem bestimmten Archiv zuzuordnen. Das
erleichtert die Pflege bei vielen Mailings und bietet zus&auml;tzliche
Optionen f&uuml;r die statistische Auswertung. In der Auswahlliste
finden Sie alle Archive, die Sie bisher definiert haben. Mehr &uuml;ber
Archive lesen Sie in Kapitel . Sie m&uuml;ssen nicht unbedingt ein
Archiv ausw&auml;hlen, das Mailing funktioniert auch ohne Zuordnung.
Au&szlig;erdem k&ouml;nnen Sie die Zuordnung zu einem Archiv sp&auml;ter
vornehmen, und auch wieder &auml;ndern.</P>]]></content>
</HelpBalloon>
